libgal/__init__.py
libgal/modules/DatabaseAPI.py
libgal/modules/FSUtils.py
libgal/modules/Logger.py
libgal/modules/MLS.py
libgal/modules/ODBCTools.py
libgal/modules/SQLAlchemy.py
libgal/modules/SQLMemory.py
libgal/modules/Sqlite.py
libgal/modules/Teradata.py
libgal/modules/Utils.py
libgal/modules/__init__.py
libgal/modules/DatabaseAPI.py
libgal/modules/FSUtils.py
libgal/modules/Logger.py
libgal/modules/MLS.py
libgal/modules/ODBCTools.py
libgal/modules/SQLAlchemy.py
libgal/modules/SQLMemory.py
libgal/modules/Sqlite.py
libgal/modules/Teradata.py
libgal/modules/Utils.py
libgal/modules/__init__.py
libgal-1.0.4.dist-info/METADATA
libgal-1.0.4.dist-info/WHEEL
libgal-1.0.4.dist-info/licenses/LICENSE.txt
libgal-1.0.4.dist-info/RECORD
