Metadata-Version: 2.3
Name: libgal
Version: 1.0.4
Summary: Librería para la simplificación del código en diversos proyectos de Python
Project-URL: Homepage, https://github.com/jeanmgonzalez/libgal
Project-URL: Bug Tracker, https://github.com/jeanmgonzalez/libgal/issues
Author-email: Jean Manuel González Mejía <ebrainding@gmail.com>, Julián Leandro Giraldez <juliangiraldez@outlook.com>, Sebastian Wilwerth <sebastian.wilwerth@gmail.com>
License: MIT License
License-File: LICENSE.txt
Classifier: License :: OSI Approved :: MIT License
Classifier: Operating System :: OS Independent
Classifier: Programming Language :: Python :: 3
Requires-Python: >=3.7
Requires-Dist: brotli
Requires-Dist: bs4
Requires-Dist: numpy>=1.26.1
Requires-Dist: pandas==2.0.0
Requires-Dist: pyodbc
Requires-Dist: python-dotenv>=0.10.2
Requires-Dist: requests
Requires-Dist: scikit-learn
Requires-Dist: selenium>=4.0.0
Requires-Dist: teradataml>=17.20.0.6
Requires-Dist: unidecode
